ccat/__init__.py
ccat/config.py
ccat/controller/__init__.py
ccat/controller/feature.py
ccat/controller/indicator.py
ccat/controller/signal.py
ccat/controller/strategy/__init__.py
ccat/controller/strategy/s_1542995464.py
ccat/model/__init__.py
ccat/model/bucket.py
ccat/model/engine.py
ccat/model/exchange.py
ccat/view/__init__.py
ccat/view/report.py
ccat-0.1.dist-info/LICENSE
ccat-0.1.dist-info/METADATA
ccat-0.1.dist-info/WHEEL
ccat-0.1.dist-info/top_level.txt
ccat-0.1.dist-info/RECORD
