Metadata-Version: 2.1
Name: ccat
Version: 0.1
Summary: modules for bit.io trading platform
Home-page: https://github.com/bliiir/bit
Author: bliiir
Author-email: hello@bit.io
License: MIT
Platform: UNKNOWN
Requires-Dist: ccxt
Requires-Dist: pandas
Requires-Dist: numpy
Requires-Dist: psycopg2
Requires-Dist: SQLAlchemy
